<annotation>
	<folder>10_826 Pallet Photos and Premium High Res Pictures_</folder>
	<filename>cardboard-boxes-on-wooden-pallet-delivery-concept-3d-illustration-illustration-isolated-on-white-sto.jpg</filename>
	<path>C:\Users\aksha.LAPTOP-KKEAULMJ\OneDrive\Documents\Python\Ineuron\pallet\10_826 Pallet Photos and Premium High Res Pictures_\cardboard-boxes-on-wooden-pallet-delivery-concept-3d-illustration-illustration-isolated-on-white-sto.jpg</path>
	<source>
		<database>Unknown</database>
	</source>
	<size>
		<width>222</width>
		<height>194</height>
		<depth>3</depth>
	</size>
	<segmented>0</segmented>
	<object>
		<name>pallet</name>
		<pose>Unspecified</pose>
		<truncated>0</truncated>
		<difficult>0</difficult>
		<bndbox>
			<xmin>41</xmin>
			<ymin>128</ymin>
			<xmax>160</xmax>
			<ymax>155</ymax>
		</bndbox>
	</object>
	<object>
		<name>box</name>
		<pose>Unspecified</pose>
		<truncated>0</truncated>
		<difficult>0</difficult>
		<bndbox>
			<xmin>44</xmin>
			<ymin>51</ymin>
			<xmax>68</xmax>
			<ymax>66</ymax>
		</bndbox>
	</object>
	<object>
		<name>box</name>
		<pose>Unspecified</pose>
		<truncated>0</truncated>
		<difficult>0</difficult>
		<bndbox>
			<xmin>66</xmin>
			<ymin>69</ymin>
			<xmax>91</xmax>
			<ymax>85</ymax>
		</bndbox>
	</object>
	<object>
		<name>box</name>
		<pose>Unspecified</pose>
		<truncated>0</truncated>
		<difficult>0</difficult>
		<bndbox>
			<xmin>69</xmin>
			<ymin>112</ymin>
			<xmax>94</xmax>
			<ymax>129</ymax>
		</bndbox>
	</object>
	<object>
		<name>box</name>
		<pose>Unspecified</pose>
		<truncated>0</truncated>
		<difficult>0</difficult>
		<bndbox>
			<xmin>122</xmin>
			<ymin>106</ymin>
			<xmax>168</xmax>
			<ymax>123</ymax>
		</bndbox>
	</object>
	<object>
		<name>box</name>
		<pose>Unspecified</pose>
		<truncated>0</truncated>
		<difficult>0</difficult>
		<bndbox>
			<xmin>43</xmin>
			<ymin>86</ymin>
			<xmax>66</xmax>
			<ymax>103</ymax>
		</bndbox>
	</object>
	<object>
		<name>box</name>
		<pose>Unspecified</pose>
		<truncated>0</truncated>
		<difficult>0</difficult>
		<bndbox>
			<xmin>43</xmin>
			<ymin>105</ymin>
			<xmax>68</xmax>
			<ymax>128</ymax>
		</bndbox>
	</object>
	<object>
		<name>box</name>
		<pose>Unspecified</pose>
		<truncated>0</truncated>
		<difficult>0</difficult>
		<bndbox>
			<xmin>92</xmin>
			<ymin>88</ymin>
			<xmax>123</xmax>
			<ymax>108</ymax>
		</bndbox>
	</object>
	<object>
		<name>box</name>
		<pose>Unspecified</pose>
		<truncated>0</truncated>
		<difficult>0</difficult>
		<bndbox>
			<xmin>96</xmin>
			<ymin>114</ymin>
			<xmax>119</xmax>
			<ymax>127</ymax>
		</bndbox>
	</object>
</annotation>
